contextframe/__init__.py
contextframe/__main__.py
contextframe/cli.py
contextframe/exceptions.py
contextframe/frame.py
contextframe/builders/__init__.py
contextframe/builders/embed.py
contextframe/builders/encode.py
contextframe/builders/enhance.py
contextframe/builders/serve.py
contextframe/embed/__init__.py
contextframe/embed/base.py
contextframe/embed/batch.py
contextframe/embed/integration.py
contextframe/embed/litellm_provider.py
contextframe/examples/__init__.py
contextframe/extract/__init__.py
contextframe/extract/base.py
contextframe/extract/batch.py
contextframe/extract/chunking.py
contextframe/extract/extractors.py
contextframe/helpers/__init__.py
contextframe/helpers/metadata_utils.py
contextframe/io/__init__.py
contextframe/io/exporter.py
contextframe/io/formats.py
contextframe/io/importer.py
contextframe/schema/__init__.py
contextframe/schema/contextframe_schema.json
contextframe/schema/contextframe_schema.py
contextframe/schema/validation.py
contextframe-0.1.1.dist-info/licenses/LICENSE
contextframe-0.1.1.dist-info/METADATA
contextframe-0.1.1.dist-info/WHEEL
contextframe-0.1.1.dist-info/entry_points.txt
contextframe-0.1.1.dist-info/top_level.txt
contextframe-0.1.1.dist-info/RECORD
