Metadata-Version: 2.4
Name: contextframe
Version: 0.1.1
Summary: ContextFrame: A global standard file specification for contextual document management with LLMs
Author-email: ContextFrame Team <contact@contextframe.org>
License-Expression: MIT
Project-URL: repository, https://github.com/greyhaven-ai/contextframe
Project-URL: documentation, https://contextframe.org
Project-URL: issues, https://github.com/greyhaven-ai/contextframe/issues
Classifier: Development Status :: 4 - Beta
Classifier: Intended Audience :: Developers
Classifier: Intended Audience :: Information Technology
Classifier: Programming Language :: Python :: 3
Classifier: Programming Language :: Python :: 3.10
Classifier: Programming Language :: Python :: 3.11
Classifier: Programming Language :: Python :: 3.12
Classifier: Topic :: Documentation
Classifier: Topic :: Software Development :: Documentation
Classifier: Topic :: Text Processing :: Markup :: Markdown
Requires-Python: <3.13,>=3.10
License-File: LICENSE
Requires-Dist: jsonschema
Requires-Dist: lance>=0.7.0
Requires-Dist: pyarrow>=14.0.2
Requires-Dist: numpy>=1.24
Requires-Dist: pyyaml>=6.0.0
Provides-Extra: dev
Requires-Dist: pytest==8.3.4; extra == "dev"
Requires-Dist: pytest-asyncio==0.25.2; extra == "dev"
Requires-Dist: pytest-cov==6.0.0; extra == "dev"
Requires-Dist: mypy==1.14.1; extra == "dev"
Requires-Dist: ruff>=0.9.5; extra == "dev"
Requires-Dist: deptry>=0.12.0; extra == "dev"
Provides-Extra: extract
Requires-Dist: semantic-text-splitter>=0.3.0; extra == "extract"
Requires-Dist: litellm>=1.0.0; extra == "extract"
Requires-Dist: tokenizers>=0.13.0; extra == "extract"
Requires-Dist: tree-sitter>=0.20.0; extra == "extract"
Requires-Dist: tree-sitter-python>=0.20.0; extra == "extract"
Requires-Dist: tree-sitter-javascript>=0.20.0; extra == "extract"
Requires-Dist: tree-sitter-typescript>=0.20.0; extra == "extract"
Requires-Dist: tree-sitter-rust>=0.20.0; extra == "extract"
Requires-Dist: tree-sitter-go>=0.19.0; extra == "extract"
Requires-Dist: tree-sitter-cpp>=0.20.0; extra == "extract"
Requires-Dist: tree-sitter-c>=0.20.0; extra == "extract"
Requires-Dist: tree-sitter-java>=0.20.0; extra == "extract"
Requires-Dist: tree-sitter-ruby>=0.20.0; extra == "extract"
Requires-Dist: tree-sitter-php>=0.19.0; extra == "extract"
Requires-Dist: tree-sitter-html>=0.19.0; extra == "extract"
Requires-Dist: tree-sitter-css>=0.19.0; extra == "extract"
Requires-Dist: tree-sitter-json>=0.19.0; extra == "extract"
Requires-Dist: tree-sitter-yaml>=0.5.0; extra == "extract"
Requires-Dist: tree-sitter-toml>=0.5.0; extra == "extract"
Requires-Dist: tree-sitter-xml>=0.6.0; extra == "extract"
Requires-Dist: tree-sitter-bash>=0.19.0; extra == "extract"
Provides-Extra: embed
Requires-Dist: sentence-transformers>=2.2.0; extra == "embed"
Requires-Dist: openai>=1.0.0; extra == "embed"
Requires-Dist: anthropic>=0.21.0; extra == "embed"
Requires-Dist: cohere>=4.0.0; extra == "embed"
Provides-Extra: enhance
Requires-Dist: openai>=1.0.0; extra == "enhance"
Requires-Dist: anthropic>=0.21.0; extra == "enhance"
Requires-Dist: tiktoken>=0.5.0; extra == "enhance"
Requires-Dist: mirascope[anthropic,litellm,openai]>=1.0.0; extra == "enhance"
Requires-Dist: pydantic>=2.0.0; extra == "enhance"
Provides-Extra: encode
Requires-Dist: opencv-python>=4.8.0; extra == "encode"
Requires-Dist: pillow>=10.0.0; extra == "encode"
Requires-Dist: ffmpeg-python>=0.2.0; extra == "encode"
Requires-Dist: numpy>=1.24; extra == "encode"
Provides-Extra: serve
Requires-Dist: mcp>=0.9.0; extra == "serve"
Requires-Dist: fastapi>=0.104.0; extra == "serve"
Requires-Dist: uvicorn[standard]>=0.24.0; extra == "serve"
Requires-Dist: sse-starlette>=1.6.0; extra == "serve"
Requires-Dist: python-jose[cryptography]>=3.3.0; extra == "serve"
Requires-Dist: python-multipart>=0.0.6; extra == "serve"
Requires-Dist: httpx>=0.25.0; extra == "serve"
Requires-Dist: slowapi>=0.1.9; extra == "serve"
Provides-Extra: all
Requires-Dist: contextframe[embed,encode,enhance,extract,io,serve]; extra == "all"
Dynamic: license-file
